README.rst
setup.py
teamcitycli.py
teamcity_cli.egg-info/PKG-INFO
teamcity_cli.egg-info/SOURCES.txt
teamcity_cli.egg-info/dependency_links.txt
teamcity_cli.egg-info/entry_points.txt
teamcity_cli.egg-info/not-zip-safe
teamcity_cli.egg-info/requires.txt
teamcity_cli.egg-info/top_level.txt