Metadata-Version: 1.1
Name: teamcity-cli
Version: 0.0.0
Summary: CLI for TeamCity CI server, built on pyteamcity
Home-page: https://github.com/SurveyMonkey/teamcity_cli
Author: Marc Abramowitz
Author-email: marca@surveymonkey.com
License: MIT
Keywords: TeamCity
Platform: UNKNOWN
Classifier: Programming Language :: Python :: 2
Classifier: Programming Language :: Python :: 2.6
Classifier: Programming Language :: Python :: 2.7
Classifier: Programming Language :: Python :: 3
Classifier: Programming Language :: Python :: 3.2
Classifier: Programming Language :: Python :: 3.3
Classifier: Programming Language :: Python :: 3.4
Classifier: Topic :: Software Development :: Testing
Classifier: Natural Language :: English
Classifier: Intended Audience :: Developers
